macromol_gym_pretrain/__init__.py
macromol_gym_pretrain/database_io.py
macromol_gym_pretrain/geometry.py
macromol_gym_pretrain/neighbors.py
macromol_gym_pretrain/pymol.py
macromol_gym_pretrain/samples.py
macromol_gym_pretrain/lightning/__init__.py
macromol_gym_pretrain/lightning/data.py
macromol_gym_pretrain/lightning/models.py
macromol_gym_pretrain/torch/__init__.py
macromol_gym_pretrain/torch/curriculum.py
macromol_gym_pretrain/torch/data.py
macromol_gym_pretrain/torch/models.py
macromol_gym_pretrain-0.2.1.dist-info/licenses/LICENSE.txt
macromol_gym_pretrain-0.2.1.dist-info/METADATA
macromol_gym_pretrain-0.2.1.dist-info/WHEEL
macromol_gym_pretrain-0.2.1.dist-info/entry_points.txt
macromol_gym_pretrain-0.2.1.dist-info/top_level.txt
macromol_gym_pretrain-0.2.1.dist-info/RECORD
