Metadata-Version: 2.4
Name: macromol_gym_pretrain
Version: 0.2.1
Summary: Self-supervised pre-training for macromolecular data
Author-email: Kale Kundert <kale@thekunderts.net>
Project-URL: Documentation, https://macromol-gym.readthedocs.io/en/latest/
Project-URL: Version Control, https://github.com/kalekundert/macromol_gym
Project-URL: Bug Tracker, https://github.com/kalekundert/macromol_gym/issues
Project-URL: Continuous Integration, https://github.com/kalekundert/macromol_gym/actions
Project-URL: Test Coverage, https://coveralls.io/github/kalekundert/macromol_gym
Classifier: Programming Language :: Python :: 3
Classifier: License :: OSI Approved :: MIT License
Requires-Python: ~=3.10
License-File: LICENSE.txt
Requires-Dist: lightning
Requires-Dist: macromol_dataframe
Requires-Dist: macromol_gym_unsupervised
Requires-Dist: macromol_voxelize
Requires-Dist: more_itertools
Requires-Dist: numpy
Requires-Dist: pipeline_func
Requires-Dist: reprfunc
Requires-Dist: scipy
Requires-Dist: torch
Requires-Dist: torch_deterministic
Requires-Dist: xxhash
Provides-Extra: test
Requires-Dist: pytest; extra == "test"
Requires-Dist: parametrize_from_file; extra == "test"
Requires-Dist: pytest_unordered; extra == "test"
Requires-Dist: pytest_tmp_files; extra == "test"
Requires-Dist: hypothesis; extra == "test"
Dynamic: license-file
